[{"id":"53.11.01","name":"Kota Waingapu"},{"id":"53.11.02","name":"Haharu"},{"id":"53.11.03","name":"Lewa"},{"id":"53.11.04","name":"Nggaha Ori Angu (Nggaha Oriangu)"},{"id":"53.11.05","name":"Tabundung"},{"id":"53.11.06","name":"Pinu Pahar (Pinupahar \/ Pirapahar)"},{"id":"53.11.07","name":"Pandawai"},{"id":"53.11.08","name":"Umalulu"},{"id":"53.11.09","name":"Rindi"},{"id":"53.11.10","name":"Pahunga Lodu"},{"id":"53.11.11","name":"Wulla Waijelu (Wula Waijelu)"},{"id":"53.11.12","name":"Paberiwai"},{"id":"53.11.13","name":"Karera"},{"id":"53.11.14","name":"Kahaungu Eti (Kahaunguweti)"},{"id":"53.11.15","name":"Matawai La Pawu (Lappau)"},{"id":"53.11.16","name":"Kambera"},{"id":"53.11.17","name":"Kambata Mapambuhang"},{"id":"53.11.18","name":"Lewa Tidahu"},{"id":"53.11.19","name":"Katala Hamu Lingu"},{"id":"53.11.20","name":"Kanatang"},{"id":"53.11.21","name":"Ngadu Ngala"},{"id":"53.11.22","name":"Mahu"}]